init_graph/__init__.py
init_graph/__main__.py
init_graph/chapters.py
init_graph/choice_option.py
init_graph/graph.py
init_graph/main.py
init_graph-0.1.1.dist-info/METADATA
init_graph-0.1.1.dist-info/WHEEL
init_graph-0.1.1.dist-info/entry_points.txt
init_graph-0.1.1.dist-info/RECORD
