Metadata-Version: 2.1
Name: init-graph
Version: 0.1.1
Summary: Added the path as environment variable
Author: vaibhavblayer
Author-email: vaibhavblayer@gmail.com
Requires-Python: >=3.11,<4.0
Classifier: Programming Language :: Python :: 3
Classifier: Programming Language :: Python :: 3.11
Requires-Dist: click (>=8.1.4,<9.0.0)
